{
	"authors": {
		"modified by": [
			"lordskelethom            2010-05-30 14:01:11",
			"Ubu                2010-05-30 18:41:43",
			"Choupom            2010-10-11 00:32:54",
			"Choupom            2010-11-21 14:07:30",
			"Choupom            2011-01-05 22:13:44",
			"clecle226            2011-02-09 12:28:39",
			"clecle226            2011-02-12 23:43:59",
			"Choupom            2011-02-13 12:24:15",
			"Choupom            2011-04-02 19:53:54",
			"Choupom            2011-04-03 23:00:57",
			"Ubu                2011-04-04 21:09:05",
			"Choupom            2011-07-02 19:23:49",
			"Fudgyking            2013-07-18 16:30:20",
			"Choupom, 2014 (Transifex)",
			"cris272, 2014 (Transifex)",
			"Guillaume V, 2018 (Transifex)",
			"Jordy Ruiz, 2018 (Transifex)",
			"Loic KASSEL, 2018 (Transifex)",
			"louis.jd.martin, 2015 (Transifex)",
			"Luttyz, 2018 (Transifex)",
			"mdecorde, 2014 (Transifex)"
		],
		"originally created by": ""
	},
	"translated strings": [
		{
			"or": "Search:",
			"tr": "Recherche :"
		},
		{
			"or": "Teams were swapped",
			"tr": "Les équipes ont été échangées"
		},
		{
			"or": "Teams were shuffled",
			"tr": "Les équipes ont été mélangées"
		},
		{
			"or": "Teams have been balanced",
			"tr": "Les équipes ont été équilibrées"
		},
		{
			"or": "All players were moved to the game",
			"tr": "Tous les joueurs ont été déplacés dans la partie"
		},
		{
			"or": "All players were moved to the red team",
			"tr": "Tous les joueurs ont été déplacés dans l'équipe rouge"
		},
		{
			"or": "All players were moved to the blue team",
			"tr": "Tous les joueurs ont été déplacés dans l'équipe bleue"
		},
		{
			"or": "All players were moved to the spectators",
			"tr": "Tous les joueurs ont été déplacés dans les spectateurs"
		},
		{
			"or": "You were moved to the red team due to team balancing",
			"tr": "Vous avez été déplacé dans l'équipe rouge pour équilibrer"
		},
		{
			"or": "You were moved to the blue team due to team balancing",
			"tr": "Vous avez été déplacé dans l'équipe bleue pour équilibrer"
		},
		{
			"or": "'%s' initiated a pause",
			"tr": "'%s' a demandé une pause"
		},
		{
			"or": "The blue flag was captured by '%s' (%.2f seconds)",
			"tr": "Le drapeau bleu a été capturé par '%s' (%.2f secondes)"
		},
		{
			"or": "The red flag was captured by '%s' (%.2f seconds)",
			"tr": "Le drapeau rouge a été capturé par '%s' (%.2f secondes)"
		},
		{
			"or": "The blue flag was captured by '%s'",
			"tr": "Le drapeau bleu a été capturé par '%s'"
		},
		{
			"or": "The red flag was captured by '%s'",
			"tr": "Le drapeau rouge a été capturé par '%s'"
		},
		{
			"or": "%s is muted by you",
			"tr": "%s est muet"
		},
		{
			"or": "Teams were locked",
			"tr": "Les équipes ont été verrouillées"
		},
		{
			"or": "Teams were unlocked",
			"tr": "Les équipes ont été déverrouillées"
		},
		{
			"or": "'%s' entered and joined the game",
			"tr": "'%s' est entré et a rejoint la partie"
		},
		{
			"or": "'%s' entered and joined the red team",
			"tr": "'%s' est entré et a rejoint l'équipe rouge"
		},
		{
			"or": "'%s' entered and joined the blue team",
			"tr": "'%s' est entré et a rejoint l'équipe bleue"
		},
		{
			"or": "'%s' entered and joined the spectators",
			"tr": "'%s' est entré et a rejoint les spectateurs"
		},
		{
			"or": "'%s' has left the game (%s)",
			"tr": "'%s' a quitté le jeu (%s)"
		},
		{
			"or": "'%s' has left the game",
			"tr": "'%s' a quitté le jeu"
		},
		{
			"or": "'%s' joined the game",
			"tr": "'%s' a rejoint la partie"
		},
		{
			"or": "'%s' joined the red team",
			"tr": "'%s' a rejoint l'équipe rouge"
		},
		{
			"or": "'%s' joined the blue team",
			"tr": "'%s' a rejoint l'équipe bleue"
		},
		{
			"or": "'%s' joined the spectators",
			"tr": "'%s' a rejoint les spectateurs"
		},
		{
			"or": "key not found",
			"tr": "touche introuvable"
		},
		{
			"or": "Move left",
			"tr": "Aller à gauche"
		},
		{
			"or": "Move right",
			"tr": "Aller à droite"
		},
		{
			"or": "Jump",
			"tr": "Sauter"
		},
		{
			"or": "Fire",
			"tr": "Tirer"
		},
		{
			"or": "Hook",
			"tr": "Grappin"
		},
		{
			"or": "Hammer",
			"tr": "Maillet"
		},
		{
			"or": "Pistol",
			"tr": "Pistolet"
		},
		{
			"or": "Shotgun",
			"tr": "Fusil à pompe"
		},
		{
			"or": "Grenade",
			"tr": "Lance-grenades"
		},
		{
			"or": "Laser",
			"tr": "Laser"
		},
		{
			"or": "Next weapon",
			"tr": "Arme suivante"
		},
		{
			"or": "Prev. weapon",
			"tr": "Arme précédente"
		},
		{
			"or": "Vote yes",
			"tr": "Voter oui"
		},
		{
			"or": "Vote no",
			"tr": "Voter non"
		},
		{
			"or": "Chat",
			"tr": "Chat"
		},
		{
			"or": "Team chat",
			"tr": "Chat équipe"
		},
		{
			"or": "Whisper",
			"tr": "Chuchoter"
		},
		{
			"or": "Show chat",
			"tr": "Montrer le chat"
		},
		{
			"or": "Emoticon",
			"tr": "Émoticônes"
		},
		{
			"or": "Spectator mode",
			"tr": "Menu spectateur"
		},
		{
			"or": "Spectate next",
			"tr": "Suivre suivant"
		},
		{
			"or": "Spectate previous",
			"tr": "Suivre précédent"
		},
		{
			"or": "Console",
			"tr": "Console locale"
		},
		{
			"or": "Remote console",
			"tr": "Console serveur"
		},
		{
			"or": "Screenshot",
			"tr": "Capture d'écran"
		},
		{
			"or": "Scoreboard",
			"tr": "Scores"
		},
		{
			"or": "Statboard",
			"tr": "Tableau des statistiques"
		},
		{
			"or": "Respawn",
			"tr": "Revivre"
		},
		{
			"or": "Ready",
			"tr": "Prêt"
		},
		{
			"or": "Add demo marker",
			"tr": "Ajouter un repère"
		},
		{
			"or": "Toggle sounds",
			"tr": "Activer les sons"
		},
		{
			"or": "Toggle dynamic camera",
			"tr": "Activer la caméra dynamique"
		},
		{
			"or": "Use OS mouse acceleration",
			"tr": "Activer l'accélération de la souris de l'OS"
		},
		{
			"or": "In-game mouse sens.",
			"tr": ""
		},
		{
			"or": "Menu mouse sens.",
			"tr": "Sensib. souris dans les menus"
		},
		{
			"or": "Enable joystick",
			"tr": "Activer le joystick"
		},
		{
			"or": "Click to cycle through all available joysticks.",
			"tr": ""
		},
		{
			"context": "In-game joystick mode",
			"or": "Relative",
			"tr": ""
		},
		{
			"context": "In-game joystick mode",
			"or": "Absolute",
			"tr": ""
		},
		{
			"or": "In-game joystick mode",
			"tr": ""
		},
		{
			"or": "In-game joystick sensitivity",
			"tr": ""
		},
		{
			"or": "Menu/Editor joystick sensitivity",
			"tr": ""
		},
		{
			"or": "Joystick jitter tolerance",
			"tr": "Tolérance aux vibrations du joystick"
		},
		{
			"or": "No joysticks found. Plug in a joystick and restart the game.",
			"tr": "Aucun joystick détecté. Banchez un joystick et redémarrez le jeu."
		},
		{
			"or": "Configure statboard",
			"tr": "Configurer le tableau des scores"
		},
		{
			"or": "Device",
			"tr": "Appareil"
		},
		{
			"or": "Status",
			"tr": "Statut"
		},
		{
			"or": "Aim bind",
			"tr": "Visée assistée"
		},
		{
			"or": "Joystick Axis #%d",
			"tr": "L'axe #%d du joystick"
		},
		{
			"context": "skins",
			"or": "body",
			"tr": "corps"
		},
		{
			"context": "skins",
			"or": "marking",
			"tr": "marques"
		},
		{
			"context": "skins",
			"or": "decoration",
			"tr": "décorations"
		},
		{
			"context": "skins",
			"or": "hands",
			"tr": "mains"
		},
		{
			"context": "skins",
			"or": "feet",
			"tr": "pieds"
		},
		{
			"context": "skins",
			"or": "eyes",
			"tr": "yeux"
		},
		{
			"or": "Name",
			"tr": "Pseudo"
		},
		{
			"or": "Suicides",
			"tr": "Suicides"
		},
		{
			"or": "Ratio",
			"tr": "Ratio"
		},
		{
			"context": "Net score",
			"or": "Net",
			"tr": "Diff."
		},
		{
			"or": "KPM",
			"tr": ""
		},
		{
			"or": "Spree",
			"tr": "Série"
		},
		{
			"or": "Best spree",
			"tr": "Meilleure série"
		},
		{
			"context": "Flag grabs",
			"or": "Grabs",
			"tr": "Grappins"
		},
		{
			"or": "%d other players",
			"tr": "%d autres joueurs"
		},
		{
			"or": "Red team",
			"tr": "Équipe rouge"
		},
		{
			"or": "Blue team",
			"tr": "Équipe bleue"
		},
		{
			"or": "'%s' called vote to change server option '%s' (%s)",
			"tr": "'%s' fait appel au vote pour changer l'option du serveur '%s' (%s)"
		},
		{
			"or": "'%s' called for vote to kick '%s' (%s)",
			"tr": "'%s' fait appel au vote pour exclure '%s' (%s)"
		},
		{
			"or": "'%s' called for vote to move '%s' to spectators (%s)",
			"tr": "'%s' fait appel au vote pour déplacer '%s' dans les spectateurs (%s)"
		},
		{
			"or": "Admin forced server option '%s' (%s)",
			"tr": "Admin a forcé l'option du serveur '%s' (%s)"
		},
		{
			"or": "Admin moved '%s' to spectator (%s)",
			"tr": "Admin a déplacé '%s' dans les spectateurs (%s)"
		},
		{
			"or": "Vote aborted",
			"tr": "Le vote est annulé"
		},
		{
			"or": "Admin forced vote yes",
			"tr": "Un admin a fait passé le vote"
		},
		{
			"or": "Vote passed",
			"tr": "Le vote est passé"
		},
		{
			"or": "Admin forced vote no",
			"tr": "Un admin a annulé le vote"
		},
		{
			"or": "Vote failed",
			"tr": "Le vote a échoué"
		},
		{
			"or": "Map changed to '%s'",
			"tr": "La carte est maintenant '%s'"
		},
		{
			"or": "All",
			"tr": "Tout le monde"
		},
		{
			"or": "Spectators",
			"tr": "Spectateurs"
		},
		{
			"or": "Team",
			"tr": "Équipe"
		},
		{
			"or": "Press %s to resume chatting",
			"tr": "Appuyez sur %s pour reprendre la discussion"
		},
		{
			"or": "Press Tab to cycle chat recipients",
			"tr": ""
		},
		{
			"or": "-Page %d/%d-",
			"tr": "-Page %d/%d-"
		},
		{
			"or": "Press Enter to confirm or Esc to cancel",
			"tr": "Appuyez sur Entrée pour confirmer ou Échap pour annuler"
		},
		{
			"or": "Press Tab to select or Esc to cancel",
			"tr": "Appuyez sur Tab pour sélectionner ou Échap pour annuler "
		},
		{
			"or": "'%s' was muted",
			"tr": "'%s' a été rendu muet"
		},
		{
			"or": "'%s' was unmuted",
			"tr": "'%s' a été rendu non muet"
		},
		{
			"or": "'%s' was added as a friend",
			"tr": "'%s' a été ajouté à la liste d'amis"
		},
		{
			"or": "'%s' was removed as a friend",
			"tr": "'%s' a été retiré de la liste d'amis"
		},
		{
			"or": "-Page %d-",
			"tr": "-Page %d-"
		},
		{
			"or": "Sudden Death",
			"tr": "Mort Subite"
		},
		{
			"or": "Game paused",
			"tr": "Partie en pause"
		},
		{
			"or": "%d player not ready",
			"tr": "%d joueur n'est pas prêt"
		},
		{
			"or": "%d players not ready",
			"tr": "%d joueurs ne sont pas prêts"
		},
		{
			"or": "Game starts in",
			"tr": "La partie commence dans"
		},
		{
			"or": "Wait for next round",
			"tr": "Patientez jusqu'à la manche suivante"
		},
		{
			"or": "%d player left",
			"tr": "%d joueur restant"
		},
		{
			"or": "%d players left",
			"tr": "%d joueurs restants"
		},
		{
			"or": "Warmup",
			"tr": "Échauffement"
		},
		{
			"or": "waiting for more players",
			"tr": ""
		},
		{
			"or": "Connection Problems...",
			"tr": "Problèmes de connexion..."
		},
		{
			"or": "Please balance teams!",
			"tr": "Veuillez équilibrer les équipes !"
		},
		{
			"or": "%ds left",
			"tr": "%ds restantes"
		},
		{
			"or": "Reason:",
			"tr": "Raison :"
		},
		{
			"or": "Vote Yes",
			"tr": ""
		},
		{
			"or": "Vote No",
			"tr": ""
		},
		{
			"or": "Spectate",
			"tr": "Caméra"
		},
		{
			"or": "Free View",
			"tr": ""
		},
		{
			"or": "Red Flag",
			"tr": ""
		},
		{
			"or": "Blue Flag",
			"tr": ""
		},
		{
			"or": "Click on a player or flag to follow it",
			"tr": ""
		},
		{
			"or": "When ready, press <%s>",
			"tr": "Une fois prêt, appuyez sur <%s>"
		},
		{
			"or": "'%s' has set a new map record: %s",
			"tr": "'%s' a établi un nouveau record sur le serveur: %s"
		},
		{
			"or": "'%s' has set a new personal record: %s",
			"tr": "'%s' a établi un nouveau record personnel: %s"
		},
		{
			"or": " (%s seconds faster)",
			"tr": "(%s secondes de moins)"
		},
		{
			"or": "'%s' finished in: %s",
			"tr": "'%s' a terminé en: %s"
		},
		{
			"or": "Game",
			"tr": "Jeu"
		},
		{
			"or": "Players",
			"tr": "Joueurs"
		},
		{
			"or": "Server info",
			"tr": "Info. serveur"
		},
		{
			"or": "Call vote",
			"tr": "Voter"
		},
		{
			"or": "Settings",
			"tr": "Options"
		},
		{
			"or": "General",
			"tr": "Général"
		},
		{
			"or": "Player",
			"tr": "Joueur"
		},
		{
			"or": "TBD",
			"tr": ""
		},
		{
			"or": "Controls",
			"tr": "Contrôles"
		},
		{
			"or": "Graphics",
			"tr": "Affichage"
		},
		{
			"or": "Sound",
			"tr": "Son"
		},
		{
			"or": "Global",
			"tr": "Global"
		},
		{
			"or": "Local",
			"tr": "Local"
		},
		{
			"or": "Demos",
			"tr": "Démos"
		},
		{
			"or": "Back",
			"tr": "Retour"
		},
		{
			"or": "Sound error",
			"tr": "Erreur de son"
		},
		{
			"or": "The audio device couldn't be initialised.",
			"tr": "Le périphérique audio n'a pas pu être initialisé."
		},
		{
			"or": "Ok",
			"tr": "Ok"
		},
		{
			"or": "Connecting to",
			"tr": "Connexion à"
		},
		{
			"or": "Downloading map",
			"tr": "Téléchargement de la carte"
		},
		{
			"or": "Loading demo",
			"tr": ""
		},
		{
			"or": "Language",
			"tr": "Langue"
		},
		{
			"or": "Flag",
			"tr": ""
		},
		{
			"or": "Rename demo",
			"tr": "Renommer la démo"
		},
		{
			"or": "Save skin",
			"tr": "Sauvegarder le skin"
		},
		{
			"or": "Password incorrect",
			"tr": "Mot de passe incorrect"
		},
		{
			"or": "Quit",
			"tr": "Quitter"
		},
		{
			"or": "Welcome to Teeworlds",
			"tr": "Bienvenue dans Teeworlds"
		},
		{
			"or": "There's an unsaved map in the editor; you may want to save it before you quit the game.",
			"tr": ""
		},
		{
			"or": "Are you sure that you want to quit?",
			"tr": "Êtes-vous sûr de vouloir quitter ?"
		},
		{
			"or": "No",
			"tr": "Non"
		},
		{
			"or": "Yes",
			"tr": "Oui"
		},
		{
			"or": "Please enter the password.",
			"tr": ""
		},
		{
			"or": "Password",
			"tr": "Mot de passe"
		},
		{
			"or": "Save password",
			"tr": "Enregistrer le mot de passe"
		},
		{
			"or": "Save password and server as favorite",
			"tr": "Sauvegarde le serveur ainsi que son mot de passe comme favoris"
		},
		{
			"or": "Abort",
			"tr": "Annuler"
		},
		{
			"or": "Try again",
			"tr": "Réessayer"
		},
		{
			"or": "%i minute left",
			"tr": "%i minute restante"
		},
		{
			"or": "%i minutes left",
			"tr": "%i minutes restantes"
		},
		{
			"or": "%i second left",
			"tr": "%i seconde restante"
		},
		{
			"or": "%i seconds left",
			"tr": "%i secondes restantes"
		},
		{
			"or": "Error loading demo",
			"tr": "Erreur pendant le chargement de la démo"
		},
		{
			"or": "Cancel",
			"tr": ""
		},
		{
			"or": "Are you sure you want to rename the demo?",
			"tr": "Êtes-vous sûr de vouloir renommer la démo ?"
		},
		{
			"or": "Error",
			"tr": "Erreur"
		},
		{
			"or": "Unable to rename the demo",
			"tr": "Impossible de renommer la démo"
		},
		{
			"or": "Are you sure you want to save your skin? If a skin with this name already exists, it will be replaced.",
			"tr": "Êtes-vous sûr de vouloir sauvegarder votre skin ? Si un skin avec le même nom existe, il sera remplacé."
		},
		{
			"or": "Unable to save the skin",
			"tr": ""
		},
		{
			"or": "Unable to save the skin with a reserved name",
			"tr": ""
		},
		{
			"or": "As this is the first time you launch the game, please enter your nick name below. It's recommended that you check the settings to adjust them to your liking before joining a server.",
			"tr": "Comme c'est la première fois que vous lancez le jeu, veuillez entrer votre pseudo ci-dessous. Vous devriez vérifier les réglages et les ajuster avant de rejoindre un serveur."
		},
		{
			"or": "Nickname",
			"tr": "Pseudonyme"
		},
		{
			"or": "Enter",
			"tr": "Démarrer"
		},
		{
			"or": "Nickname is empty.",
			"tr": "Votre pseudo est vide."
		},
		{
			"or": "Disconnected",
			"tr": "Déconnecté"
		},
		{
			"or": "The server is running a non-standard tuning on a pure game type.",
			"tr": "Le serveur utilise des paramètres non standards sur un type de jeu standard."
		},
		{
			"or": "Server",
			"tr": "Serveur"
		},
		{
			"or": "Type",
			"tr": "Type"
		},
		{
			"or": "Map",
			"tr": "Carte"
		},
		{
			"or": "Ping",
			"tr": "Ping"
		},
		{
			"or": "Race",
			"tr": ""
		},
		{
			"or": "Favorites",
			"tr": "Favoris"
		},
		{
			"or": "This server is protected by a password.",
			"tr": ""
		},
		{
			"or": "Click to remove server from favorites.",
			"tr": ""
		},
		{
			"or": "Click to add server to favorites.",
			"tr": ""
		},
		{
			"or": "Friends are online on this server.",
			"tr": ""
		},
		{
			"or": "%d servers, %d players",
			"tr": "%d serveurs, %d joueurs"
		},
		{
			"or": "Are you sure that you want to remove the filter '%s' from the server browser?",
			"tr": ""
		},
		{
			"or": "Remove filter",
			"tr": "Supprimer le filtre"
		},
		{
			"or": "Refreshing master servers",
			"tr": "Rafraîchissement des serveurs maîtres"
		},
		{
			"or": "No filter category is selected",
			"tr": "Aucune catégorie de filtre n'a été sélectionnée"
		},
		{
			"or": "Fetching server info",
			"tr": "Récupération des informations serveur"
		},
		{
			"or": "No servers found",
			"tr": "Aucun serveur trouvé"
		},
		{
			"or": "No local servers found (ports %d–%d)",
			"tr": ""
		},
		{
			"or": "No servers match your filter criteria",
			"tr": "Aucun serveur ne correspond à vos critères"
		},
		{
			"or": "Host address:",
			"tr": "Adresse serveur :"
		},
		{
			"or": "%d%% loaded",
			"tr": "%d %% chargé"
		},
		{
			"or": "%d servers",
			"tr": "%d serveurs"
		},
		{
			"or": "%d players",
			"tr": "%d joueurs"
		},
		{
			"or": "Double click to join your friend.",
			"tr": ""
		},
		{
			"context": "Playing '(gametype)' on '(map)'",
			"or": "Playing '%s' on '%s'",
			"tr": "Joue à '%s' sur '%s'"
		},
		{
			"context": "Watching '(gametype)' on '(map)'",
			"or": "Watching '%s' on '%s'",
			"tr": "Regarde du '%s' sur '%s'"
		},
		{
			"or": "Click to delete this friend.",
			"tr": ""
		},
		{
			"or": "Online players (%d)",
			"tr": "Joueurs en ligne (%d)"
		},
		{
			"or": "Online clanmates (%d)",
			"tr": "Coéquipiers en ligne (%d)"
		},
		{
			"context": "friends (server browser)",
			"or": "Offline (%d)",
			"tr": "Hors ligne (%d)"
		},
		{
			"or": "Clan",
			"tr": "Clan"
		},
		{
			"or": "Add friend/clan",
			"tr": "Ajouter un ami/clan"
		},
		{
			"or": "Add friend",
			"tr": "Ajouter un ami"
		},
		{
			"or": "Add clan",
			"tr": "Ajouter le clan"
		},
		{
			"or": "Are you sure that you want to remove the player '%s' from your friends list?",
			"tr": ""
		},
		{
			"or": "Are you sure that you want to remove the clan '%s' from your friends list?",
			"tr": ""
		},
		{
			"or": "Remove friend",
			"tr": "Supprimer des amis"
		},
		{
			"or": "New filter",
			"tr": "Nouveau filtre"
		},
		{
			"or": "Server filter",
			"tr": "Filtres"
		},
		{
			"or": "Has people playing",
			"tr": "Au moins un joueur"
		},
		{
			"or": "Count players only",
			"tr": "Seulement les joueurs"
		},
		{
			"or": "Server not full",
			"tr": "Le serveur n'est pas plein"
		},
		{
			"or": "Show friends only",
			"tr": "Montrer les amis"
		},
		{
			"or": "Hide bots",
			"tr": "Cacher les bots"
		},
		{
			"or": "No password",
			"tr": "Pas de mot de passe"
		},
		{
			"or": "Compatible version",
			"tr": "Version compatible"
		},
		{
			"or": "Standard gametype",
			"tr": "Types de jeu standards"
		},
		{
			"or": "Standard map",
			"tr": "Cartes standards"
		},
		{
			"or": "Game types:",
			"tr": "Types de jeu :"
		},
		{
			"or": "Include servers with this gametype.",
			"tr": ""
		},
		{
			"or": "Exclude servers with this gametype.",
			"tr": ""
		},
		{
			"context": "clear gametype filters",
			"or": "Clear",
			"tr": "Effacer"
		},
		{
			"or": "Maximum ping:",
			"tr": "Ping maximum :"
		},
		{
			"or": "Server address:",
			"tr": "Adresse :"
		},
		{
			"or": "Flag:",
			"tr": ""
		},
		{
			"or": "Difficulty:",
			"tr": "Niveau :"
		},
		{
			"or": "Reset filter",
			"tr": "Remise à zéro du filtre"
		},
		{
			"or": "Server details",
			"tr": "Détails du serveur"
		},
		{
			"or": "Map:",
			"tr": "Carte :"
		},
		{
			"or": "Game type:",
			"tr": "Type de jeu :"
		},
		{
			"or": "Version:",
			"tr": "Version :"
		},
		{
			"context": "Server difficulty",
			"or": "Casual",
			"tr": "Détendu"
		},
		{
			"context": "Server difficulty",
			"or": "Normal",
			"tr": "Normal"
		},
		{
			"context": "Server difficulty",
			"or": "Competitive",
			"tr": "Compétitif"
		},
		{
			"or": "Click to remove the player from your friends.",
			"tr": ""
		},
		{
			"or": "Click to add the player to your friends.",
			"tr": ""
		},
		{
			"or": "Refresh",
			"tr": "Rafraîchir"
		},
		{
			"or": "Connect",
			"tr": "Connecter"
		},
		{
			"or": "Length",
			"tr": "Longueur"
		},
		{
			"or": "Date",
			"tr": ""
		},
		{
			"or": "Close",
			"tr": "Fermer"
		},
		{
			"or": "Demofile: %s",
			"tr": "Démo : %s"
		},
		{
			"or": "Parent Folder",
			"tr": "Dossier parent"
		},
		{
			"or": "Folder",
			"tr": "Dossier"
		},
		{
			"or": "Invalid Demo",
			"tr": "Démo invalide"
		},
		{
			"or": "Demo details",
			"tr": "Détails de la démo"
		},
		{
			"or": "Recorded",
			"tr": "Enregistré"
		},
		{
			"or": "Delete",
			"tr": "Supprimer"
		},
		{
			"or": "Are you sure that you want to delete the demo '%s'?",
			"tr": ""
		},
		{
			"or": "Delete demo",
			"tr": "Supprimer la démo"
		},
		{
			"or": "Rename",
			"tr": "Renommer"
		},
		{
			"or": "Fetch Info",
			"tr": ""
		},
		{
			"or": "Open",
			"tr": "Ouvrir"
		},
		{
			"context": "DemoBrowser",
			"or": "Play",
			"tr": "Lire"
		},
		{
			"or": "Unable to delete the demo",
			"tr": "Impossible de supprimer la démo"
		},
		{
			"or": "Created",
			"tr": "Créé"
		},
		{
			"or": "Version",
			"tr": "Version"
		},
		{
			"or": "Netversion",
			"tr": "Netversion"
		},
		{
			"or": "Markers",
			"tr": "Repères"
		},
		{
			"or": "%.3f KiB",
			"tr": "%.3f Kio"
		},
		{
			"or": "Size",
			"tr": "Taille"
		},
		{
			"or": "Crc",
			"tr": "Crc"
		},
		{
			"or": "Teams are locked",
			"tr": "Les équipes sont verrouillées"
		},
		{
			"or": "Only %d active players are allowed",
			"tr": "Seulement %d joueurs actifs sont permis"
		},
		{
			"or": "Teams are locked. Time to wait before changing team: %02d:%02d",
			"tr": "Les équipes sont verrouillées. Vous pourrez changer d'équipe dans : %02d:%02d"
		},
		{
			"or": "Game options",
			"tr": "Options de jeu"
		},
		{
			"or": "locked",
			"tr": "bloqué"
		},
		{
			"or": "Spectating",
			"tr": "Spectateur"
		},
		{
			"or": "Join red",
			"tr": "Rouge"
		},
		{
			"or": "Joined red",
			"tr": "Rouge"
		},
		{
			"or": "Join blue",
			"tr": "Bleu"
		},
		{
			"or": "Joined blue",
			"tr": "Bleu"
		},
		{
			"or": "Join",
			"tr": "Rejoindre"
		},
		{
			"or": "Joined",
			"tr": "En jeu"
		},
		{
			"or": "Disconnect",
			"tr": "Partir"
		},
		{
			"or": "Stop record",
			"tr": "Arrêter"
		},
		{
			"or": "Record",
			"tr": "Enregistrer"
		},
		{
			"or": "Player options",
			"tr": "Joueurs"
		},
		{
			"or": "Address",
			"tr": "Adresse"
		},
		{
			"context": "With",
			"or": "Yes",
			"tr": "Oui"
		},
		{
			"context": "Without/None",
			"or": "No",
			"tr": "Non"
		},
		{
			"or": "Favorite",
			"tr": "Favori"
		},
		{
			"or": "Mute broadcasts",
			"tr": "Cacher les messages serveur (broadcasts)"
		},
		{
			"or": "Game info",
			"tr": "Info. jeu"
		},
		{
			"or": "Game type",
			"tr": "Type de jeu"
		},
		{
			"or": "Difficulty",
			"tr": "Niveau"
		},
		{
			"or": "Score limit",
			"tr": "Limite de score"
		},
		{
			"or": "Time limit",
			"tr": "Temps limite"
		},
		{
			"or": "MOTD",
			"tr": "MOTD"
		},
		{
			"or": "Option",
			"tr": "Option"
		},
		{
			"or": "Wait for current vote to end before calling a new one.",
			"tr": "Attendez la fin du vote en cours avant de lancer un autre vote."
		},
		{
			"or": "You must wait %d seconds before making another vote",
			"tr": "Vous devez patientez pendant %d secondes avant de faire appel à un autre vote"
		},
		{
			"or": "Spectators aren't allowed to start a vote.",
			"tr": "Les spectateurs ne peuvent faire appel à un vote."
		},
		{
			"or": "Change settings",
			"tr": "Changer les options"
		},
		{
			"or": "Kick player",
			"tr": "Exclure un joueur"
		},
		{
			"or": "Move player to spectators",
			"tr": "Déplacer un joueur dans les spectateurs"
		},
		{
			"or": "Server does not allow voting to kick players",
			"tr": "Le serveur n'autorise pas à exclure des joueurs"
		},
		{
			"or": "Kick voting requires %d players on the server",
			"tr": "Il doit y avoir au moins %d joueurs sur le serveur pour pouvoir exclure une personne"
		},
		{
			"or": "Server does not allow voting to move players to spectators",
			"tr": "Le serveur n'autorise pas à déplacer des joueurs dans les spectateurs"
		},
		{
			"or": "Force vote",
			"tr": "Forcer le vote"
		},
		{
			"or": "Remove",
			"tr": "Supprimer"
		},
		{
			"or": "Vote description:",
			"tr": "Description :"
		},
		{
			"or": "Vote command:",
			"tr": "Commande :"
		},
		{
			"or": "Add",
			"tr": "Ajouter"
		},
		{
			"or": "Hue:",
			"tr": "Teinte :"
		},
		{
			"or": "Sat:",
			"tr": "Saturation :"
		},
		{
			"or": "Lgt:",
			"tr": "Lumière :"
		},
		{
			"or": "Alp:",
			"tr": "Alpha :"
		},
		{
			"or": "Skins",
			"tr": "Skins"
		},
		{
			"or": "Theme",
			"tr": "Thème"
		},
		{
			"or": "Dynamic Camera",
			"tr": "Caméra dynamique"
		},
		{
			"or": "Smooth Camera",
			"tr": ""
		},
		{
			"or": "Switch weapon on pickup",
			"tr": "Sélectionner l'arme ramassée"
		},
		{
			"or": "Show name plates",
			"tr": "Montrer les pseudos"
		},
		{
			"or": "Always show name plates",
			"tr": "Toujours afficher les pseudos"
		},
		{
			"or": "Use team colors for name plates",
			"tr": "Utiliser la couleur des équipes"
		},
		{
			"or": "Show in-game HUD",
			"tr": ""
		},
		{
			"or": "Hide player's score",
			"tr": ""
		},
		{
			"or": "Show user IDs",
			"tr": "Montrer les ID des joueurs"
		},
		{
			"or": "Show social",
			"tr": "Activer les fonctionnalités sociales"
		},
		{
			"context": "Show chat messages from",
			"or": "everyone",
			"tr": "tout le monde"
		},
		{
			"context": "Show chat messages from",
			"or": "friends only",
			"tr": "seulement les amis"
		},
		{
			"context": "Show chat messages from",
			"or": "no one",
			"tr": "personne"
		},
		{
			"or": "Show chat messages from",
			"tr": "Montrer les messages de "
		},
		{
			"or": "Enable colored server broadcasts",
			"tr": "Activer les messages serveur colorés (broadcasts)"
		},
		{
			"or": "Disable whisper feature",
			"tr": "Désactiver les messages privés"
		},
		{
			"or": "Client",
			"tr": "Client"
		},
		{
			"or": "Skip the main menu",
			"tr": "Passer le menu principal"
		},
		{
			"or": "Wide menu",
			"tr": ""
		},
		{
			"or": "Menu background opacity",
			"tr": ""
		},
		{
			"or": "Automatically record demos",
			"tr": "Enregistrer automatiquement une démo"
		},
		{
			"or": "Max",
			"tr": "Max"
		},
		{
			"or": "Automatically take game over screenshot",
			"tr": "Sauvegarder les résultats à la fin de la partie"
		},
		{
			"or": "Reset",
			"tr": "Réinitialiser"
		},
		{
			"or": "Reset general settings",
			"tr": ""
		},
		{
			"or": "Are you sure that you want to reset the general settings to their defaults?",
			"tr": ""
		},
		{
			"or": "Customize",
			"tr": "Personnaliser"
		},
		{
			"or": "Custom colors",
			"tr": "Couleurs personnalisées"
		},
		{
			"or": "Tee",
			"tr": "Tee"
		},
		{
			"or": "Normal:",
			"tr": "Normal :"
		},
		{
			"or": "Team:",
			"tr": "Équipe :"
		},
		{
			"or": "Personal",
			"tr": "Informations personnelles"
		},
		{
			"or": "Save",
			"tr": "Sauvegarder"
		},
		{
			"or": "Randomize",
			"tr": ""
		},
		{
			"or": "Are you sure that you want to delete the skin '%s'?",
			"tr": ""
		},
		{
			"or": "Delete skin",
			"tr": "Supprimer le skin"
		},
		{
			"or": "Basic",
			"tr": "Basique"
		},
		{
			"or": "Custom",
			"tr": "Perso"
		},
		{
			"or": "Unable to delete the skin",
			"tr": "Le skin n'a pas pu être supprimé"
		},
		{
			"or": "Mouse",
			"tr": "Souris"
		},
		{
			"or": "Joystick",
			"tr": "Joystick"
		},
		{
			"or": "Movement",
			"tr": "Mouvement"
		},
		{
			"or": "Weapon",
			"tr": "Arme"
		},
		{
			"or": "Voting",
			"tr": "Vote"
		},
		{
			"or": "Misc",
			"tr": "Divers"
		},
		{
			"or": "Reset controls",
			"tr": ""
		},
		{
			"or": "Are you sure that you want to reset the controls to their defaults?",
			"tr": ""
		},
		{
			"or": "Kills",
			"tr": ""
		},
		{
			"or": "Deaths",
			"tr": "Morts"
		},
		{
			"or": "The ratio of kills to deaths.",
			"tr": ""
		},
		{
			"or": "Net score",
			"tr": "Différence victime/mort"
		},
		{
			"or": "The number of kills minus the number of deaths.",
			"tr": ""
		},
		{
			"or": "Kills per minute",
			"tr": ""
		},
		{
			"or": "Current spree",
			"tr": "Série actuelle"
		},
		{
			"or": "Weapons stats",
			"tr": "Statistiques des armes"
		},
		{
			"or": "The proportion of kills gotten with each weapon.",
			"tr": ""
		},
		{
			"or": "Flag grabs",
			"tr": "Drapeaux attrapés"
		},
		{
			"or": "The number of times that the flag was touched in CTF (1 point).",
			"tr": ""
		},
		{
			"or": "Flag captures",
			"tr": "Drapeaux validés"
		},
		{
			"or": "The number of times that the flag was captured in CTF (100 points).",
			"tr": ""
		},
		{
			"or": "Screen",
			"tr": "Écran"
		},
		{
			"or": "Fullscreen",
			"tr": "Plein écran"
		},
		{
			"or": "Borderless window",
			"tr": "Fenêtre sans contours"
		},
		{
			"or": "Screen:",
			"tr": "Écran :"
		},
		{
			"or": "Anti Aliasing",
			"tr": "Anticrénelage"
		},
		{
			"or": "Enable OpenGL ES",
			"tr": ""
		},
		{
			"or": "V-Sync",
			"tr": "V-Sync"
		},
		{
			"or": "Limit Fps",
			"tr": "Limite d'IPS"
		},
		{
			"or": "Max fps",
			"tr": "IPS max"
		},
		{
			"or": "Texture",
			"tr": "Textures"
		},
		{
			"or": "Quality Textures",
			"tr": "Textures haute qualité"
		},
		{
			"or": "Texture Compression",
			"tr": "Compression des textures"
		},
		{
			"or": "High Detail",
			"tr": "Tous les détails"
		},
		{
			"or": "Resolution",
			"tr": "Résolution"
		},
		{
			"or": "Recommended",
			"tr": "Recommandé"
		},
		{
			"or": "Other",
			"tr": "Autre"
		},
		{
			"or": "Current: %dx%d (%d:%d)",
			"tr": "Actuel : %dx%d (%d:%d)"
		},
		{
			"or": "Reset graphics settings",
			"tr": ""
		},
		{
			"or": "Are you sure that you want to reset the graphics settings to their defaults?",
			"tr": ""
		},
		{
			"or": "Play background music",
			"tr": "Activer la musique de fond"
		},
		{
			"or": "Mute when window is inactive",
			"tr": ""
		},
		{
			"or": "Detail",
			"tr": "Détail"
		},
		{
			"or": "Sample rate",
			"tr": "Fréquence"
		},
		{
			"or": "Volume",
			"tr": "Volume"
		},
		{
			"or": "Load the sound system",
			"tr": "Charger les sons"
		},
		{
			"or": "Use sounds",
			"tr": "Activer le son"
		},
		{
			"or": "Reset sound settings",
			"tr": ""
		},
		{
			"or": "Are you sure that you want to reset the sound settings to their defaults?",
			"tr": ""
		},
		{
			"or": "You must restart the game for all settings to take effect.",
			"tr": "Les changements prendront effet au prochain redémarrage."
		},
		{
			"or": "You must reconnect to change identity.",
			"tr": "Vous devez vous reconnecter pour changer d'identité."
		},
		{
			"or": "You have to wait %1.0f seconds to change identity.",
			"tr": "Vous devez attendre %1.0f secondes pour changer d'identité"
		},
		{
			"or": "Local server",
			"tr": "Serveur local"
		},
		{
			"or": "Editor",
			"tr": "Éditeur"
		},
		{
			"or": "Play",
			"tr": "Jouer"
		},
		{
			"or": "Teeworlds %s is out! Download it at www.teeworlds.com!",
			"tr": "Teeworlds %s est sorti ! Téléchargez-le sur www.teeworlds.com !"
		},
		{
			"or": "Time limit: %d min",
			"tr": "Temps limite : %d min"
		},
		{
			"context": "rounds (scoreboard)",
			"or": "Match",
			"tr": "Match"
		},
		{
			"or": "Game over",
			"tr": "Fin de la partie"
		},
		{
			"or": "Round over",
			"tr": "La manche est terminée"
		},
		{
			"or": "Map record",
			"tr": "Record de la carte"
		},
		{
			"or": "Time",
			"tr": "Temps"
		},
		{
			"or": "Score",
			"tr": "Score"
		},
		{
			"or": "REC %3d:%02d",
			"tr": "REC %3d:%02d"
		},
		{
			"or": "%s wins!",
			"tr": "%s a gagné !"
		},
		{
			"or": "Draw!",
			"tr": "Égalité !"
		},
		{
			"or": "Round over!",
			"tr": "La manche est terminée !"
		},
		{
			"or": "Free-View",
			"tr": "Vue libre"
		}
	]
}